MysqlZhuruTianshuSqliLabsZhuruShouce/README.md
MysqlZhuruTianshuSqliLabsZhuruShouce/__init__.py
MysqlZhuruTianshuSqliLabsZhuruShouce/__main__.py
MysqlZhuruTianshuSqliLabsZhuruShouce/file.pdf
MysqlZhuruTianshuSqliLabsZhuruShouce/index.html
mysql_zhuru_tianshu_sqli_labs_zhuru_shouce-2024.3.2.0.dist-info/METADATA
mysql_zhuru_tianshu_sqli_labs_zhuru_shouce-2024.3.2.0.dist-info/WHEEL
mysql_zhuru_tianshu_sqli_labs_zhuru_shouce-2024.3.2.0.dist-info/entry_points.txt
mysql_zhuru_tianshu_sqli_labs_zhuru_shouce-2024.3.2.0.dist-info/top_level.txt
mysql_zhuru_tianshu_sqli_labs_zhuru_shouce-2024.3.2.0.dist-info/RECORD
